{
  "users": [
    {
      "name": "Vaibhav",
      "age": 22,
      "email": "vaibhav@test.com",
      "id": "ae3e"
    },
    {
      "name": "Peter",
      "age": 38,
      "email": "peter@test.com",
      "id": "4e81"
    },
    {
      "name": "Tom",
      "age": 45,
      "email": "tom@test.com",
      "id": "60dc"
    },
    {
      "name": "Jerry",
      "age": 19,
      "email": "jerry@test.com",
      "id": "e1fe"
    },
    {
      "name": "Sam",
      "age": 56,
      "email": "sam@test.com",
      "id": "ccdc"
    }
  ],
  "$schema": "./node_modules/json-server/schema.json"
}